sqlalchemy_window/__init__.py
sqlalchemy_window/_select.py
sqlalchemy_window/_window.py
sqlalchemy_window/py.typed
sqlalchemy_window-0.2.0.dist-info/METADATA
sqlalchemy_window-0.2.0.dist-info/WHEEL
sqlalchemy_window-0.2.0.dist-info/licenses/LICENSE
sqlalchemy_window-0.2.0.dist-info/RECORD
