Metadata-Version: 2.1
Name: sqlalchemy_window
Version: 0.2.0
Summary: A SQLAlchemy plugin to add support for PostgreSQL WINDOW clause
Project-URL: Repository, https://github.com/waterfountain1996/sqlalchemy-window
Author-email: Roman Necheporenko <roman@waterfountain.one>
License-Expression: MIT
License-File: LICENSE
Classifier: License :: OSI Approved :: MIT License
Classifier: Operating System :: OS Independent
Classifier: Programming Language :: Python :: 3
Requires-Python: >=3.8
Requires-Dist: sqlalchemy>=2.0
